{
	"song": {
		"sectionLengths": [],
		"player1": "3d-bf",
		"events": [],
		"gfVersion": "nothing",
		"notes": [
			{
				"lengthInSteps": 160000,
				"typeOfSection": 0,
				"sectionNotes": [],
				"altAnim": false,
				"changeBPM": false,
				"mustHitSection": false,
				"bpm": 130
			},
			{
				"lengthInSteps": 16,
				"typeOfSection": 0,
				"sectionNotes": [
					[
						3185.8407079646,
						5,
						132.743362831858
					],
					[
						3982.30088495575,
						4,
						132.743362831858
					],
					[
						3584.07079646018,
						6,
						132.743362831858
					]
				],
				"altAnim": false,
				"bpm": 130,
				"changeBPM": false,
				"mustHitSection": false
			},
			{
				"sectionNotes": [
					[
						4247.78761061947,
						3,
						0
					],
					[
						4513.27433628319,
						3,
						0
					],
					[
						4778.7610619469,
						3,
						0
					],
					[
						5044.24778761062,
						3,
						0
					]
				],
				"typeOfSection": 0,
				"lengthInSteps": 16,
				"gfSection": false,
				"altAnim": false,
				"mustHitSection": true,
				"changeBPM": false,
				"bpm": 130
			},
			{
				"sectionNotes": [
					[
						7433.62831858407,
						0,
						0
					],
					[
						7699.11504424779,
						0,
						0
					],
					[
						7964.6017699115,
						2,
						0
					],
					[
						8230.08849557522,
						2,
						0
					],
					[
						8296.46017699115,
						2,
						0
					],
					[
						8097.34513274336,
						1,
						0
					],
					[
						8362.83185840708,
						1,
						0
					]
				],
				"typeOfSection": 0,
				"lengthInSteps": 16,
				"gfSection": false,
				"altAnim": false,
				"mustHitSection": true,
				"changeBPM": false,
				"bpm": 113
			},
			{
				"sectionNotes": [],
				"typeOfSection": 0,
				"lengthInSteps": 16,
				"gfSection": false,
				"altAnim": false,
				"mustHitSection": true,
				"changeBPM": false,
				"bpm": 113
			},
			{
				"sectionNotes": [
					[
						11681.4159292035,
						4,
						0
					],
					[
						12079.6460176991,
						7,
						0
					],
					[
						12477.8761061947,
						5,
						0
					]
				],
				"typeOfSection": 0,
				"lengthInSteps": 16,
				"gfSection": false,
				"altAnim": false,
				"mustHitSection": true,
				"changeBPM": false,
				"bpm": 113
			},
			{
				"sectionNotes": [
					[
						12743.3628318584,
						2,
						0
					],
					[
						13008.8495575221,
						2,
						0
					],
					[
						13274.3362831858,
						2,
						0
					],
					[
						13539.8230088496,
						2,
						0
					]
				],
				"typeOfSection": 0,
				"lengthInSteps": 16,
				"gfSection": false,
				"altAnim": false,
				"mustHitSection": false,
				"changeBPM": false,
				"bpm": 113
			},
			{
				"sectionNotes": [
					[
						16194.6902654867,
						0,
						0
					],
					[
						15929.203539823,
						0,
						0
					],
					[
						16460.1769911504,
						3,
						0
					],
					[
						16725.6637168142,
						3,
						0
					],
					[
						16792.0353982301,
						3,
						0
					],
					[
						16592.9203539823,
						1,
						0
					],
					[
						16858.407079646,
						1,
						0
					]
				],
				"typeOfSection": 0,
				"lengthInSteps": 16,
				"gfSection": false,
				"altAnim": false,
				"mustHitSection": false,
				"changeBPM": false,
				"bpm": 113
			},
			{
				"sectionNotes": [
					[
						16991.1504424779,
						2,
						0
					],
					[
						17256.6371681416,
						1,
						0
					],
					[
						17522.1238938053,
						3,
						0
					],
					[
						17654.8672566372,
						3,
						0
					],
					[
						17787.610619469,
						1,
						0
					],
					[
						18053.0973451327,
						0,
						0
					],
					[
						18318.5840707965,
						2,
						0
					],
					[
						18584.0707964602,
						3,
						0
					],
					[
						18716.814159292,
						3,
						0
					],
					[
						18849.5575221239,
						1,
						0
					]
				],
				"typeOfSection": 0,
				"lengthInSteps": 16,
				"gfSection": false,
				"altAnim": false,
				"mustHitSection": false,
				"changeBPM": false,
				"bpm": 113
			},
			{
				"sectionNotes": [
					[
						20176.9911504425,
						1,
						0
					],
					[
						20309.7345132743,
						3,
						0
					],
					[
						20508.8495575221,
						0,
						0
					],
					[
						20575.221238938,
						2,
						0
					],
					[
						20707.9646017699,
						1,
						0
					],
					[
						20973.4513274336,
						1,
						0
					],
					[
						19115.0442477876,
						3,
						0
					],
					[
						19380.5309734513,
						2,
						0
					],
					[
						19646.017699115,
						0,
						0
					],
					[
						19911.5044247788,
						2,
						0
					],
					[
						20044.2477876106,
						2,
						0
					],
					[
						20243.3628318584,
						1,
						0
					],
					[
						20442.4778761062,
						0,
						0
					]
				],
				"typeOfSection": 0,
				"lengthInSteps": 16,
				"gfSection": false,
				"altAnim": false,
				"mustHitSection": false,
				"changeBPM": false,
				"bpm": 113
			},
			{
				"sectionNotes": [
					[
						21238.9380530973,
						2,
						132.743362831858
					],
					[
						21504.4247787611,
						1,
						132.743362831858
					],
					[
						21769.9115044248,
						2,
						0
					],
					[
						21902.6548672566,
						2,
						0
					],
					[
						22035.3982300885,
						0,
						132.743362831858
					],
					[
						22300.8849557522,
						3,
						132.743362831858
					],
					[
						22566.3716814159,
						1,
						132.743362831858
					],
					[
						22831.8584070796,
						2,
						0
					],
					[
						22964.6017699115,
						2,
						0
					],
					[
						23097.3451327434,
						3,
						132.743362831858
					],
					[
						21238.9380530973,
						5,
						0
					],
					[
						21504.4247787611,
						5,
						0
					],
					[
						21769.9115044248,
						5,
						0
					],
					[
						22035.3982300885,
						5,
						0
					]
				],
				"typeOfSection": 0,
				"lengthInSteps": 16,
				"gfSection": false,
				"altAnim": false,
				"mustHitSection": true,
				"changeBPM": false,
				"bpm": 113
			},
			{
				"sectionNotes": [
					[
						23362.8318584071,
						0,
						132.743362831858
					],
					[
						23628.3185840708,
						2,
						132.743362831858
					],
					[
						23893.8053097345,
						1,
						132.743362831858
					],
					[
						24159.2920353982,
						3,
						0
					],
					[
						24292.0353982301,
						3,
						0
					],
					[
						24424.7787610619,
						1,
						0
					],
					[
						24557.5221238938,
						3,
						0
					],
					[
						24491.1504424779,
						0,
						0
					],
					[
						24690.2654867257,
						2,
						0
					],
					[
						24756.6371681416,
						0,
						0
					],
					[
						24823.0088495575,
						2,
						0
					],
					[
						24955.7522123894,
						1,
						0
					],
					[
						25221.2389380531,
						1,
						0
					],
					[
						23362.8318584071,
						4,
						0
					],
					[
						23628.3185840708,
						4,
						0
					],
					[
						23893.8053097345,
						4,
						0
					],
					[
						24159.2920353982,
						7,
						0
					],
					[
						24424.7787610619,
						7,
						0
					],
					[
						24690.2654867257,
						7,
						0
					],
					[
						24955.7522123894,
						7,
						0
					]
				],
				"typeOfSection": 0,
				"lengthInSteps": 16,
				"gfSection": false,
				"altAnim": false,
				"mustHitSection": true,
				"changeBPM": false,
				"bpm": 113
			},
			{
				"sectionNotes": [
					[
						26946.9026548672,
						2,
						0
					],
					[
						26814.1592920354,
						0,
						0
					],
					[
						25486.7256637168,
						2,
						0
					],
					[
						25752.2123893805,
						3,
						0
					],
					[
						26017.6991150442,
						0,
						0
					],
					[
						26150.4424778761,
						0,
						0
					],
					[
						26283.185840708,
						1,
						0
					],
					[
						26548.6725663717,
						2,
						0
					],
					[
						26681.4159292035,
						3,
						0
					],
					[
						27146.017699115,
						0,
						0
					],
					[
						27278.7610619469,
						0,
						0
					],
					[
						27079.6460176991,
						3,
						0
					],
					[
						27212.389380531,
						3,
						0
					],
					[
						27345.1327433628,
						1,
						0
					],
					[
						27477.8761061947,
						1,
						0
					],
					[
						25486.7256637168,
						4,
						0
					],
					[
						25752.2123893805,
						4,
						0
					],
					[
						26017.6991150442,
						4,
						0
					],
					[
						26283.185840708,
						4,
						0
					]
				],
				"typeOfSection": 0,
				"lengthInSteps": 16,
				"gfSection": false,
				"altAnim": false,
				"mustHitSection": false,
				"changeBPM": false,
				"bpm": 113
			},
			{
				"sectionNotes": [
					[
						27743.3628318584,
						0,
						0
					],
					[
						28008.8495575221,
						3,
						0
					],
					[
						28672.5663716814,
						2,
						0
					],
					[
						28738.9380530973,
						1,
						0
					],
					[
						27876.1061946903,
						2,
						0
					],
					[
						28407.0796460177,
						2,
						0
					],
					[
						28539.8230088495,
						2,
						0
					],
					[
						28141.592920354,
						1,
						132.743362831858
					],
					[
						28805.3097345133,
						0,
						0
					],
					[
						28938.0530973451,
						2,
						0
					],
					[
						29004.4247787611,
						3,
						0
					],
					[
						29070.796460177,
						2,
						0
					],
					[
						29137.1681415929,
						3,
						0
					],
					[
						29203.5398230088,
						0,
						0
					],
					[
						29336.2831858407,
						1,
						0
					],
					[
						29469.0265486726,
						0,
						0
					],
					[
						29601.7699115044,
						2,
						0
					],
					[
						27610.6194690265,
						7,
						0
					],
					[
						27876.1061946903,
						7,
						0
					],
					[
						28141.592920354,
						7,
						0
					],
					[
						28407.0796460177,
						7,
						0
					],
					[
						28672.5663716814,
						6,
						0
					],
					[
						28938.0530973451,
						6,
						0
					],
					[
						29203.5398230088,
						6,
						0
					]
				],
				"typeOfSection": 0,
				"lengthInSteps": 16,
				"gfSection": false,
				"altAnim": false,
				"mustHitSection": false,
				"changeBPM": false,
				"bpm": 113
			},
			{
				"sectionNotes": [
					[
						30000,
						1,
						132.743362831858
					],
					[
						29734.5132743363,
						3,
						132.743362831858
					],
					[
						30265.4867256637,
						3,
						0
					],
					[
						30398.2300884956,
						3,
						0
					],
					[
						30530.9734513274,
						0,
						0
					],
					[
						30796.4601769911,
						1,
						0
					],
					[
						30929.203539823,
						2,
						0
					],
					[
						31194.6902654867,
						2,
						0
					],
					[
						31061.9469026549,
						0,
						0
					],
					[
						31327.4336283186,
						3,
						0
					],
					[
						31393.8053097345,
						1,
						0
					],
					[
						31460.1769911504,
						0,
						0
					],
					[
						31592.9203539823,
						3,
						0
					],
					[
						31526.5486725664,
						2,
						0
					],
					[
						31725.6637168141,
						2,
						132.743362831858
					]
				],
				"typeOfSection": 0,
				"lengthInSteps": 16,
				"gfSection": false,
				"altAnim": false,
				"mustHitSection": true,
				"changeBPM": false,
				"bpm": 113
			},
			{
				"sectionNotes": [
					[
						31991.1504424779,
						0,
						0
					],
					[
						32123.8938053097,
						1,
						0
					],
					[
						32256.6371681416,
						3,
						0
					],
					[
						32389.3805309734,
						0,
						132.743362831858
					],
					[
						32654.8672566372,
						3,
						0
					],
					[
						32787.610619469,
						3,
						0
					],
					[
						33053.0973451327,
						3,
						0
					],
					[
						33451.3274336283,
						2,
						0
					],
					[
						33716.814159292,
						1,
						0
					],
					[
						33584.0707964602,
						3,
						0
					],
					[
						33859.5132743363,
						0,
						0
					],
					[
						33185.8407079646,
						0,
						0
					],
					[
						33252.2123893805,
						1,
						0
					],
					[
						33318.5840707965,
						0,
						0
					],
					[
						33384.9557522124,
						1,
						0
					],
					[
						32920.3539823009,
						2,
						0
					],
					[
						32986.7256637168,
						1,
						0
					]
				],
				"typeOfSection": 0,
				"lengthInSteps": 16,
				"gfSection": false,
				"altAnim": false,
				"mustHitSection": true,
				"changeBPM": false,
				"bpm": 113
			},
			{
				"sectionNotes": [
					[
						34247.7876106195,
						0,
						0
					],
					[
						34380.5309734513,
						0,
						0
					],
					[
						34513.2743362832,
						1,
						0
					],
					[
						34778.7610619469,
						0,
						0
					],
					[
						35044.2477876106,
						2,
						0
					],
					[
						35309.7345132743,
						3,
						0
					],
					[
						35575.221238938,
						1,
						0
					],
					[
						35707.9646017699,
						1,
						0
					],
					[
						35840.7079646018,
						0,
						132.743362831858
					]
				],
				"typeOfSection": 0,
				"lengthInSteps": 16,
				"gfSection": false,
				"altAnim": false,
				"mustHitSection": false,
				"changeBPM": false,
				"bpm": 113
			},
			{
				"sectionNotes": [
					[
						36238.9380530974,
						2,
						0
					],
					[
						36504.4247787611,
						2,
						0
					],
					[
						36637.1681415929,
						0,
						132.743362831858
					],
					[
						37433.6283185841,
						1,
						0
					],
					[
						37566.3716814159,
						3,
						0
					],
					[
						37699.1150442478,
						0,
						0
					],
					[
						37831.8584070796,
						2,
						0
					],
					[
						37964.6017699115,
						3,
						0
					],
					[
						38097.3451327434,
						0,
						0
					],
					[
						36902.6548672566,
						1,
						132.743362831858
					],
					[
						37168.1415929204,
						3,
						0
					]
				],
				"typeOfSection": 0,
				"lengthInSteps": 16,
				"gfSection": false,
				"altAnim": false,
				"mustHitSection": false,
				"changeBPM": false,
				"bpm": 113
			},
			{
				"sectionNotes": [
					[
						38561.9469026549,
						0,
						0
					],
					[
						39424.778761062,
						1,
						0
					],
					[
						38230.0884955752,
						2,
						0
					],
					[
						38362.8318584071,
						2,
						0
					],
					[
						38495.5752212389,
						3,
						0
					],
					[
						38628.3185840708,
						3,
						0
					],
					[
						39823.0088495575,
						0,
						0
					],
					[
						39955.7522123894,
						0,
						0
					],
					[
						38694.6902654867,
						0,
						0
					],
					[
						38893.8053097345,
						2,
						0
					],
					[
						38761.0619469026,
						2,
						0
					],
					[
						39026.5486725664,
						0,
						0
					],
					[
						39159.2920353982,
						3,
						0
					],
					[
						39557.5221238938,
						2,
						0
					],
					[
						40088.4955752212,
						1,
						132.743362831858
					]
				],
				"typeOfSection": 0,
				"lengthInSteps": 16,
				"gfSection": false,
				"altAnim": false,
				"mustHitSection": false,
				"changeBPM": false,
				"bpm": 113
			},
			{
				"sectionNotes": [
					[
						40486.7256637168,
						0,
						0
					],
					[
						40353.982300885,
						2,
						0
					],
					[
						40752.2123893805,
						2,
						0
					],
					[
						41415.9292035398,
						3,
						0
					],
					[
						40884.9557522124,
						0,
						0
					],
					[
						41017.6991150442,
						0,
						0
					],
					[
						41150.4424778761,
						0,
						0
					],
					[
						41283.185840708,
						1,
						0
					],
					[
						41349.5575221239,
						1,
						0
					],
					[
						41216.814159292,
						2,
						0
					],
					[
						41814.1592920354,
						3,
						0
					],
					[
						41681.4159292035,
						1,
						0
					],
					[
						41946.9026548673,
						1,
						0
					],
					[
						42079.6460176991,
						0,
						0
					],
					[
						42212.389380531,
						3,
						0
					],
					[
						42345.1327433628,
						1,
						0
					]
				],
				"typeOfSection": 0,
				"lengthInSteps": 16,
				"gfSection": false,
				"altAnim": false,
				"mustHitSection": false,
				"changeBPM": false,
				"bpm": 113
			},
			{
				"sectionNotes": [
					[
						42743.3628318584,
						1,
						0
					],
					[
						42876.1061946903,
						1,
						0
					],
					[
						43539.8230088496,
						3,
						132.743362831858
					],
					[
						43805.3097345133,
						0,
						132.743362831858
					],
					[
						44070.796460177,
						2,
						0
					],
					[
						44203.5398230089,
						2,
						0
					],
					[
						44336.2831858407,
						1,
						132.743362831858
					],
					[
						43274.3362831858,
						1,
						132.743362831858
					],
					[
						43008.8495575221,
						0,
						132.743362831858
					]
				],
				"typeOfSection": 0,
				"lengthInSteps": 16,
				"gfSection": false,
				"altAnim": false,
				"mustHitSection": true,
				"changeBPM": false,
				"bpm": 113
			},
			{
				"sectionNotes": [
					[
						44734.5132743363,
						2,
						0
					],
					[
						45000,
						2,
						0
					],
					[
						45132.7433628319,
						0,
						132.743362831858
					],
					[
						45398.2300884956,
						3,
						132.743362831858
					],
					[
						45663.7168141593,
						0,
						132.743362831858
					],
					[
						45929.203539823,
						1,
						0
					],
					[
						46061.9469026549,
						3,
						0
					],
					[
						46194.6902654867,
						0,
						0
					],
					[
						46327.4336283186,
						2,
						0
					],
					[
						46460.1769911504,
						3,
						0
					],
					[
						46592.9203539823,
						0,
						0
					]
				],
				"typeOfSection": 0,
				"lengthInSteps": 16,
				"gfSection": false,
				"altAnim": false,
				"mustHitSection": true,
				"changeBPM": false,
				"bpm": 113
			},
			{
				"sectionNotes": [
					[
						47057.5221238938,
						0,
						0
					],
					[
						47522.1238938053,
						0,
						0
					],
					[
						47654.8672566372,
						3,
						132.743362831858
					],
					[
						47920.3539823009,
						1,
						0
					],
					[
						48053.0973451328,
						2,
						132.743362831858
					],
					[
						46725.6637168142,
						2,
						0
					],
					[
						46858.407079646,
						2,
						0
					],
					[
						46991.1504424779,
						3,
						0
					],
					[
						47123.8938053097,
						3,
						0
					],
					[
						48318.5840707965,
						0,
						0
					],
					[
						48451.3274336283,
						0,
						0
					],
					[
						48584.0707964602,
						1,
						132.743362831858
					],
					[
						47190.2654867257,
						0,
						0
					],
					[
						47256.6371681416,
						2,
						0
					],
					[
						47389.3805309735,
						2,
						0
					]
				],
				"typeOfSection": 0,
				"lengthInSteps": 16,
				"gfSection": false,
				"altAnim": false,
				"mustHitSection": true,
				"changeBPM": false,
				"bpm": 113
			},
			{
				"sectionNotes": [
					[
						48849.5575221239,
						3,
						0
					],
					[
						48982.3008849558,
						0,
						0
					],
					[
						49247.7876106195,
						3,
						0
					],
					[
						49712.389380531,
						3,
						0
					],
					[
						49911.5044247788,
						2,
						132.743362831858
					],
					[
						50707.9646017699,
						3,
						0
					],
					[
						50840.7079646018,
						1,
						0
					],
					[
						49778.7610619469,
						0,
						0
					],
					[
						49778.7610619469,
						0,
						0
					],
					[
						49845.1327433628,
						1,
						0
					],
					[
						49513.2743362832,
						1,
						0
					],
					[
						49646.0176991151,
						1,
						0
					],
					[
						49380.5309734513,
						1,
						0
					],
					[
						50176.9911504425,
						0,
						0
					],
					[
						50309.7345132744,
						2,
						0
					],
					[
						50442.4778761062,
						0,
						0
					],
					[
						50575.2212389381,
						1,
						0
					]
				],
				"typeOfSection": 0,
				"lengthInSteps": 16,
				"gfSection": false,
				"altAnim": false,
				"mustHitSection": true,
				"changeBPM": false,
				"bpm": 113
			},
			{
				"sectionNotes": [
					[
						50973.4513274336,
						1,
						132.743362831858
					],
					[
						51238.9380530974,
						3,
						0
					],
					[
						51371.6814159292,
						1,
						0
					],
					[
						51637.1681415929,
						0,
						0
					],
					[
						51902.6548672567,
						0,
						0
					],
					[
						52035.3982300885,
						3,
						132.743362831858
					],
					[
						51769.9115044248,
						2,
						0
					],
					[
						52566.371681416,
						3,
						132.743362831858
					],
					[
						52300.8849557522,
						2,
						0
					],
					[
						52831.8584070797,
						2,
						0
					],
					[
						52964.6017699115,
						1,
						0
					],
					[
						50973.4513274336,
						7,
						1991.15044247788
					]
				],
				"typeOfSection": 0,
				"lengthInSteps": 16,
				"gfSection": false,
				"altAnim": false,
				"mustHitSection": false,
				"changeBPM": false,
				"bpm": 113
			},
			{
				"sectionNotes": [
					[
						53097.3451327434,
						0,
						0
					],
					[
						53362.8318584071,
						0,
						0
					],
					[
						53495.575221239,
						0,
						0
					],
					[
						54026.5486725664,
						3,
						0
					],
					[
						53893.8053097345,
						1,
						0
					],
					[
						54159.2920353983,
						2,
						132.743362831858
					],
					[
						54424.778761062,
						0,
						0
					],
					[
						54557.5221238938,
						1,
						0
					],
					[
						54690.2654867257,
						2,
						0
					],
					[
						54955.7522123894,
						2,
						0
					],
					[
						55088.4955752213,
						0,
						0
					],
					[
						53761.0619469027,
						0,
						0
					],
					[
						53097.3451327434,
						4,
						663.716814159292
					],
					[
						53893.8053097345,
						5,
						663.716814159292
					],
					[
						54690.2654867257,
						6,
						663.716814159292
					],
					[
						55088.4955752212,
						4,
						265.486725663717
					]
				],
				"typeOfSection": 0,
				"lengthInSteps": 16,
				"gfSection": false,
				"altAnim": false,
				"mustHitSection": false,
				"changeBPM": false,
				"bpm": 113
			},
			{
				"sectionNotes": [
					[
						55221.2389380531,
						1,
						132.743362831858
					],
					[
						55486.7256637168,
						3,
						0
					],
					[
						55619.4690265487,
						1,
						0
					],
					[
						56150.4424778761,
						0,
						0
					],
					[
						55752.2123893806,
						2,
						0
					],
					[
						55884.9557522124,
						3,
						0
					],
					[
						56017.6991150443,
						2,
						0
					],
					[
						56415.9292035399,
						0,
						0
					],
					[
						56482.3008849558,
						3,
						0
					],
					[
						56349.5575221239,
						2,
						0
					],
					[
						56283.185840708,
						1,
						0
					],
					[
						56548.6725663717,
						2,
						0
					],
					[
						56814.1592920354,
						0,
						132.743362831858
					],
					[
						57079.6460176992,
						3,
						0
					],
					[
						57212.389380531,
						2,
						0
					],
					[
						55486.7256637168,
						7,
						1725.66371681416
					]
				],
				"typeOfSection": 0,
				"lengthInSteps": 16,
				"gfSection": false,
				"altAnim": false,
				"mustHitSection": false,
				"changeBPM": false,
				"bpm": 113
			},
			{
				"sectionNotes": [
					[
						57345.1327433629,
						1,
						0
					],
					[
						57477.8761061947,
						3,
						0
					],
					[
						57610.6194690266,
						3,
						0
					],
					[
						57743.3628318584,
						1,
						0
					],
					[
						57876.1061946903,
						3,
						0
					],
					[
						58008.8495575222,
						1,
						0
					],
					[
						58141.592920354,
						0,
						0
					],
					[
						58274.3362831859,
						3,
						0
					],
					[
						58407.0796460177,
						2,
						132.743362831858
					],
					[
						58672.5663716814,
						0,
						0
					],
					[
						58938.0530973452,
						3,
						0
					],
					[
						58971.2389380531,
						2,
						132.743362831858
					],
					[
						58805.3097345133,
						1,
						0
					],
					[
						59203.5398230089,
						0,
						132.743362831858
					],
					[
						57345.1327433629,
						4,
						0
					],
					[
						57477.8761061947,
						6,
						0
					],
					[
						57610.6194690266,
						7,
						0
					],
					[
						57743.3628318584,
						5,
						0
					],
					[
						57876.1061946903,
						6,
						0
					],
					[
						58008.8495575222,
						7,
						0
					],
					[
						58141.592920354,
						4,
						0
					],
					[
						58274.3362831859,
						7,
						0
					],
					[
						58407.0796460177,
						5,
						132.743362831858
					],
					[
						58672.5663716814,
						7,
						132.743362831858
					],
					[
						58938.0530973452,
						4,
						265.486725663717
					]
				],
				"typeOfSection": 0,
				"lengthInSteps": 16,
				"gfSection": false,
				"altAnim": false,
				"mustHitSection": false,
				"changeBPM": false,
				"bpm": 113
			},
			{
				"sectionNotes": [
					[
						59469.0265486726,
						1,
						132.743362831858
					],
					[
						59734.5132743363,
						3,
						0
					],
					[
						59867.2566371682,
						1,
						0
					],
					[
						60132.7433628319,
						0,
						0
					],
					[
						60398.2300884956,
						0,
						0
					],
					[
						60530.9734513275,
						3,
						132.743362831858
					],
					[
						60265.4867256637,
						2,
						0
					],
					[
						61061.9469026549,
						3,
						132.743362831858
					],
					[
						60796.4601769912,
						2,
						0
					],
					[
						61327.4336283186,
						2,
						0
					],
					[
						61460.1769911505,
						1,
						0
					],
					[
						59469.0265486726,
						6,
						265.486725663717
					]
				],
				"typeOfSection": 0,
				"lengthInSteps": 16,
				"gfSection": false,
				"altAnim": false,
				"mustHitSection": true,
				"changeBPM": false,
				"bpm": 113
			},
			{
				"sectionNotes": [
					[
						61592.9203539823,
						0,
						0
					],
					[
						61858.407079646,
						0,
						0
					],
					[
						61991.1504424779,
						0,
						0
					],
					[
						62522.1238938053,
						3,
						0
					],
					[
						62389.3805309735,
						1,
						0
					],
					[
						62654.8672566372,
						2,
						132.743362831858
					],
					[
						62920.3539823009,
						0,
						0
					],
					[
						63053.0973451328,
						1,
						0
					],
					[
						63185.8407079646,
						2,
						0
					],
					[
						63451.3274336283,
						2,
						0
					],
					[
						63584.0707964602,
						0,
						0
					],
					[
						62256.6371681416,
						0,
						0
					],
					[
						61592.9203539823,
						4,
						265.486725663717
					],
					[
						62389.3805309735,
						5,
						265.486725663717
					],
					[
						63185.8407079646,
						4,
						265.486725663717
					],
					[
						63318.5840707965,
						5,
						132.743362831858
					]
				],
				"typeOfSection": 0,
				"lengthInSteps": 16,
				"gfSection": false,
				"altAnim": false,
				"mustHitSection": true,
				"changeBPM": false,
				"bpm": 113
			},
			{
				"sectionNotes": [
					[
						63716.8141592921,
						1,
						132.743362831858
					],
					[
						63982.3008849558,
						3,
						0
					],
					[
						64115.0442477876,
						1,
						0
					],
					[
						64646.0176991151,
						0,
						0
					],
					[
						64247.7876106195,
						2,
						0
					],
					[
						64380.5309734514,
						3,
						0
					],
					[
						64513.2743362832,
						2,
						0
					],
					[
						64911.5044247788,
						0,
						0
					],
					[
						64977.8761061947,
						3,
						0
					],
					[
						64845.1327433629,
						2,
						0
					],
					[
						64778.7610619469,
						1,
						0
					],
					[
						65044.2477876106,
						2,
						0
					],
					[
						65309.7345132744,
						0,
						132.743362831858
					],
					[
						65575.2212389381,
						3,
						0
					],
					[
						65707.9646017699,
						2,
						0
					],
					[
						63982.3008849558,
						7,
						265.486725663717
					]
				],
				"typeOfSection": 0,
				"lengthInSteps": 16,
				"gfSection": false,
				"altAnim": false,
				"mustHitSection": true,
				"changeBPM": false,
				"bpm": 113
			},
			{
				"sectionNotes": [
					[
						65840.7079646018,
						1,
						0
					],
					[
						65973.4513274336,
						3,
						0
					],
					[
						66106.1946902655,
						3,
						0
					],
					[
						66238.9380530974,
						1,
						0
					],
					[
						66371.6814159292,
						3,
						0
					],
					[
						66504.4247787611,
						1,
						0
					],
					[
						66637.1681415929,
						0,
						0
					],
					[
						66769.9115044248,
						3,
						0
					],
					[
						66902.6548672567,
						2,
						132.743362831858
					],
					[
						67168.1415929204,
						0,
						0
					],
					[
						67433.6283185841,
						3,
						0
					],
					[
						67466.8141592921,
						2,
						132.743362831858
					],
					[
						67300.8849557522,
						1,
						0
					],
					[
						67699.1150442478,
						0,
						132.743362831858
					],
					[
						65840.7079646018,
						4,
						0
					],
					[
						66106.1946902655,
						7,
						0
					],
					[
						66769.9115044248,
						7,
						0
					],
					[
						66902.6548672567,
						5,
						0
					],
					[
						66238.9380530974,
						6,
						0
					],
					[
						65973.4513274336,
						5,
						0
					],
					[
						66371.6814159292,
						7,
						0
					],
					[
						66504.4247787611,
						4,
						0
					],
					[
						66637.1681415929,
						6,
						0
					],
					[
						67168.1415929204,
						4,
						0
					],
					[
						67433.6283185841,
						6,
						265.486725663717
					]
				],
				"typeOfSection": 0,
				"lengthInSteps": 16,
				"gfSection": false,
				"altAnim": false,
				"mustHitSection": true,
				"changeBPM": false,
				"bpm": 113
			},
			{
				"sectionNotes": [],
				"typeOfSection": 0,
				"lengthInSteps": 16,
				"gfSection": false,
				"altAnim": false,
				"mustHitSection": true,
				"changeBPM": false,
				"bpm": 113
			},
			{
				"sectionNotes": [],
				"typeOfSection": 0,
				"lengthInSteps": 16,
				"gfSection": false,
				"altAnim": false,
				"mustHitSection": true,
				"changeBPM": false,
				"bpm": 113
			},
			{
				"sectionNotes": [],
				"typeOfSection": 0,
				"lengthInSteps": 16,
				"gfSection": false,
				"altAnim": false,
				"mustHitSection": false,
				"changeBPM": false,
				"bpm": 113
			},
			{
				"sectionNotes": [],
				"typeOfSection": 0,
				"lengthInSteps": 16,
				"gfSection": false,
				"altAnim": false,
				"mustHitSection": false,
				"changeBPM": false,
				"bpm": 113
			},
			{
				"sectionNotes": [],
				"typeOfSection": 0,
				"lengthInSteps": 16,
				"gfSection": false,
				"altAnim": false,
				"mustHitSection": true,
				"changeBPM": false,
				"bpm": 113
			},
			{
				"sectionNotes": [],
				"typeOfSection": 0,
				"lengthInSteps": 16,
				"gfSection": false,
				"altAnim": false,
				"mustHitSection": true,
				"changeBPM": false,
				"bpm": 113
			},
			{
				"sectionNotes": [],
				"typeOfSection": 0,
				"lengthInSteps": 16,
				"gfSection": false,
				"altAnim": false,
				"mustHitSection": false,
				"changeBPM": false,
				"bpm": 113
			},
			{
				"sectionNotes": [],
				"typeOfSection": 0,
				"lengthInSteps": 16,
				"gfSection": false,
				"altAnim": false,
				"mustHitSection": false,
				"changeBPM": false,
				"bpm": 113
			},
			{
				"sectionNotes": [
					[
						86548.6725663717,
						1,
						0
					],
					[
						86681.4159292036,
						1,
						0
					],
					[
						85486.7256637169,
						3,
						0
					],
					[
						85752.2123893806,
						2,
						132.743362831858
					],
					[
						86283.185840708,
						0,
						0
					],
					[
						86814.1592920354,
						3,
						0
					],
					[
						86946.9026548673,
						3,
						0
					]
				],
				"typeOfSection": 0,
				"lengthInSteps": 16,
				"gfSection": false,
				"altAnim": false,
				"mustHitSection": false,
				"changeBPM": false,
				"bpm": 113
			},
			{
				"sectionNotes": [
					[
						87079.6460176992,
						7,
						0
					],
					[
						87345.1327433629,
						6,
						132.743362831858
					],
					[
						87610.6194690266,
						0,
						0
					],
					[
						87676.9911504425,
						1,
						132.743362831858
					],
					[
						87876.1061946903,
						3,
						0
					],
					[
						88141.592920354,
						0,
						398.230088495575
					],
					[
						88407.0796460178,
						1,
						132.743362831858
					],
					[
						88672.5663716815,
						2,
						398.230088495575
					]
				],
				"typeOfSection": 0,
				"lengthInSteps": 16,
				"gfSection": false,
				"altAnim": false,
				"mustHitSection": true,
				"changeBPM": false,
				"bpm": 113
			},
			{
				"sectionNotes": [
					[
						89734.5132743363,
						3,
						132.743362831858
					],
					[
						90000.0000000001,
						2,
						398.230088495575
					],
					[
						90530.9734513275,
						0,
						132.743362831858
					],
					[
						90796.4601769912,
						1,
						0
					],
					[
						90929.2035398231,
						1,
						0
					],
					[
						91061.9469026549,
						2,
						0
					],
					[
						91194.6902654868,
						2,
						0
					]
				],
				"typeOfSection": 0,
				"lengthInSteps": 16,
				"gfSection": false,
				"altAnim": false,
				"mustHitSection": true,
				"changeBPM": false,
				"bpm": 113
			},
			{
				"sectionNotes": [
					[
						91858.4070796461,
						0,
						0
					],
					[
						91327.4336283186,
						4,
						132.743362831858
					],
					[
						91592.9203539824,
						7,
						132.743362831858
					],
					[
						91924.778761062,
						3,
						0
					],
					[
						92123.8938053098,
						1,
						0
					],
					[
						92389.3805309735,
						2,
						132.743362831858
					],
					[
						92920.3539823009,
						2,
						132.743362831858
					]
				],
				"typeOfSection": 0,
				"lengthInSteps": 16,
				"gfSection": false,
				"altAnim": false,
				"mustHitSection": false,
				"changeBPM": false,
				"bpm": 113
			},
			{
				"sectionNotes": [
					[
						95044.2477876107,
						1,
						0
					],
					[
						95176.9911504425,
						1,
						0
					],
					[
						93982.3008849558,
						3,
						0
					],
					[
						94247.7876106195,
						2,
						132.743362831858
					],
					[
						94778.7610619469,
						0,
						0
					],
					[
						95309.7345132744,
						3,
						0
					],
					[
						95442.4778761062,
						3,
						0
					]
				],
				"typeOfSection": 0,
				"lengthInSteps": 16,
				"gfSection": false,
				"altAnim": false,
				"mustHitSection": false,
				"changeBPM": false,
				"bpm": 113
			},
			{
				"sectionNotes": [
					[
						95575.2212389381,
						7,
						0
					],
					[
						95840.7079646018,
						6,
						132.743362831858
					],
					[
						96106.1946902655,
						0,
						0
					],
					[
						96172.5663716815,
						1,
						132.743362831858
					],
					[
						96371.6814159293,
						3,
						0
					],
					[
						96637.168141593,
						0,
						398.230088495575
					],
					[
						96902.6548672567,
						1,
						132.743362831858
					],
					[
						97168.1415929204,
						2,
						398.230088495575
					]
				],
				"typeOfSection": 0,
				"lengthInSteps": 16,
				"gfSection": false,
				"altAnim": false,
				"mustHitSection": true,
				"changeBPM": false,
				"bpm": 113
			},
			{
				"sectionNotes": [
					[
						98230.0884955753,
						3,
						132.743362831858
					],
					[
						98495.575221239,
						2,
						398.230088495575
					],
					[
						99026.5486725664,
						0,
						132.743362831858
					],
					[
						99292.0353982301,
						1,
						0
					],
					[
						99424.778761062,
						1,
						0
					],
					[
						99557.5221238939,
						2,
						0
					],
					[
						99690.2654867257,
						2,
						0
					]
				],
				"typeOfSection": 0,
				"lengthInSteps": 16,
				"gfSection": false,
				"altAnim": false,
				"mustHitSection": true,
				"changeBPM": false,
				"bpm": 113
			},
			{
				"sectionNotes": [
					[
						100353.982300885,
						4,
						0
					],
					[
						99823.0088495576,
						0,
						132.743362831858
					],
					[
						100088.495575221,
						3,
						132.743362831858
					],
					[
						100420.353982301,
						7,
						0
					],
					[
						100619.469026549,
						5,
						0
					],
					[
						100884.955752212,
						6,
						132.743362831858
					],
					[
						101415.92920354,
						6,
						132.743362831858
					],
					[
						100353.982300885,
						0,
						398.230088495575
					],
					[
						100884.955752212,
						2,
						398.230088495575
					],
					[
						101415.92920354,
						3,
						398.230088495575
					],
					[
						100619.469026549,
						1,
						132.743362831858
					],
					[
						101150.442477876,
						0,
						132.743362831858
					],
					[
						101681.415929204,
						1,
						132.743362831858
					]
				],
				"typeOfSection": 0,
				"lengthInSteps": 16,
				"gfSection": false,
				"altAnim": false,
				"mustHitSection": true,
				"changeBPM": false,
				"bpm": 113
			},
			{
				"sectionNotes": [
					[
						101946.902654867,
						2,
						0
					],
					[
						102212.389380531,
						1,
						0
					],
					[
						102477.876106195,
						3,
						0
					],
					[
						102610.619469027,
						3,
						0
					],
					[
						102743.362831858,
						1,
						0
					],
					[
						103008.849557522,
						0,
						0
					],
					[
						103274.336283186,
						2,
						0
					],
					[
						103539.82300885,
						3,
						0
					],
					[
						103672.566371681,
						3,
						0
					],
					[
						103805.309734513,
						1,
						0
					],
					[
						103008.849557522,
						1,
						0
					]
				],
				"typeOfSection": 0,
				"lengthInSteps": 16,
				"gfSection": false,
				"altAnim": false,
				"mustHitSection": false,
				"changeBPM": false,
				"bpm": 113
			},
			{
				"sectionNotes": [
					[
						105132.743362832,
						1,
						0
					],
					[
						105265.486725664,
						3,
						0
					],
					[
						105464.601769911,
						0,
						0
					],
					[
						105530.973451327,
						2,
						0
					],
					[
						105663.716814159,
						1,
						0
					],
					[
						105929.203539823,
						1,
						0
					],
					[
						104070.796460177,
						3,
						0
					],
					[
						104336.283185841,
						2,
						0
					],
					[
						104601.769911504,
						0,
						0
					],
					[
						104867.256637168,
						2,
						0
					],
					[
						105000,
						2,
						0
					],
					[
						105199.115044248,
						1,
						0
					],
					[
						105398.230088496,
						0,
						0
					],
					[
						104070.796460177,
						1,
						0
					]
				],
				"typeOfSection": 0,
				"lengthInSteps": 16,
				"gfSection": false,
				"altAnim": false,
				"mustHitSection": false,
				"changeBPM": false,
				"bpm": 113
			},
			{
				"sectionNotes": [
					[
						106194.690265487,
						2,
						132.743362831858
					],
					[
						106460.17699115,
						1,
						132.743362831858
					],
					[
						106725.663716814,
						2,
						0
					],
					[
						106858.407079646,
						2,
						0
					],
					[
						106991.150442478,
						0,
						132.743362831858
					],
					[
						107256.637168142,
						3,
						132.743362831858
					],
					[
						107522.123893805,
						1,
						132.743362831858
					],
					[
						107787.610619469,
						2,
						0
					],
					[
						107920.353982301,
						2,
						0
					],
					[
						108053.097345133,
						3,
						132.743362831858
					],
					[
						106194.690265487,
						5,
						0
					],
					[
						106460.17699115,
						5,
						0
					],
					[
						106725.663716814,
						5,
						0
					],
					[
						106991.150442478,
						5,
						0
					],
					[
						106194.690265487,
						7,
						0
					],
					[
						107256.637168142,
						2,
						0
					]
				],
				"typeOfSection": 0,
				"lengthInSteps": 16,
				"gfSection": false,
				"altAnim": false,
				"mustHitSection": true,
				"changeBPM": false,
				"bpm": 113
			},
			{
				"sectionNotes": [
					[
						108318.584070796,
						0,
						132.743362831858
					],
					[
						108584.07079646,
						2,
						132.743362831858
					],
					[
						108849.557522124,
						1,
						132.743362831858
					],
					[
						109115.044247788,
						3,
						0
					],
					[
						109247.787610619,
						3,
						0
					],
					[
						109380.530973451,
						1,
						0
					],
					[
						109513.274336283,
						3,
						0
					],
					[
						109446.902654867,
						0,
						0
					],
					[
						109646.017699115,
						2,
						0
					],
					[
						109712.389380531,
						0,
						0
					],
					[
						109778.761061947,
						2,
						0
					],
					[
						109911.504424779,
						1,
						0
					],
					[
						110176.991150442,
						1,
						0
					],
					[
						108318.584070796,
						4,
						0
					],
					[
						108584.07079646,
						4,
						0
					],
					[
						108849.557522124,
						4,
						0
					],
					[
						109115.044247788,
						7,
						0
					],
					[
						109380.530973451,
						7,
						0
					],
					[
						109646.017699115,
						7,
						0
					],
					[
						108318.584070797,
						5,
						0
					],
					[
						109115.044247788,
						6,
						0
					],
					[
						110243.362831858,
						5,
						0
					],
					[
						110276.548672566,
						4,
						0
					],
					[
						110376.10619469,
						5,
						0
					],
					[
						110409.292035398,
						4,
						0
					],
					[
						110044.247787611,
						4,
						0
					],
					[
						110110.619469027,
						4,
						0
					],
					[
						109911.504424779,
						6,
						0
					],
					[
						109977.876106195,
						6,
						0
					],
					[
						110176.991150443,
						6,
						0
					],
					[
						110210.176991151,
						7,
						0
					],
					[
						110309.734513274,
						6,
						0
					],
					[
						110342.920353982,
						7,
						0
					],
					[
						108318.584070797,
						1,
						0
					]
				],
				"typeOfSection": 0,
				"lengthInSteps": 16,
				"gfSection": false,
				"altAnim": false,
				"mustHitSection": true,
				"changeBPM": false,
				"bpm": 113
			},
			{
				"sectionNotes": [
					[
						111902.654867257,
						2,
						0
					],
					[
						111769.911504425,
						0,
						0
					],
					[
						110442.477876106,
						2,
						0
					],
					[
						110707.96460177,
						3,
						0
					],
					[
						110973.451327434,
						0,
						0
					],
					[
						111106.194690265,
						0,
						0
					],
					[
						111238.938053097,
						1,
						0
					],
					[
						111504.424778761,
						2,
						0
					],
					[
						111637.168141593,
						3,
						0
					],
					[
						112101.769911504,
						0,
						0
					],
					[
						112234.513274336,
						0,
						0
					],
					[
						112035.398230088,
						3,
						0
					],
					[
						112168.14159292,
						3,
						0
					],
					[
						112300.884955752,
						1,
						0
					],
					[
						112433.628318584,
						1,
						0
					],
					[
						110442.477876106,
						4,
						0
					],
					[
						110707.96460177,
						4,
						0
					],
					[
						110973.451327434,
						4,
						0
					],
					[
						111238.938053097,
						4,
						0
					],
					[
						110442.477876106,
						7,
						0
					],
					[
						111504.424778761,
						1,
						0
					]
				],
				"typeOfSection": 0,
				"lengthInSteps": 16,
				"gfSection": false,
				"altAnim": false,
				"mustHitSection": false,
				"changeBPM": false,
				"bpm": 113
			},
			{
				"sectionNotes": [
					[
						112699.115044248,
						0,
						0
					],
					[
						112964.601769911,
						3,
						0
					],
					[
						113628.318584071,
						2,
						0
					],
					[
						113694.690265487,
						1,
						0
					],
					[
						112831.85840708,
						2,
						0
					],
					[
						113362.831858407,
						2,
						0
					],
					[
						113495.575221239,
						2,
						0
					],
					[
						113097.345132743,
						1,
						132.743362831858
					],
					[
						113761.061946903,
						0,
						0
					],
					[
						113893.805309734,
						2,
						0
					],
					[
						113960.17699115,
						3,
						0
					],
					[
						114026.548672566,
						2,
						0
					],
					[
						114092.920353982,
						3,
						0
					],
					[
						114159.292035398,
						0,
						0
					],
					[
						114292.03539823,
						1,
						0
					],
					[
						114424.778761062,
						0,
						0
					],
					[
						114557.522123894,
						2,
						0
					],
					[
						112566.371681416,
						7,
						0
					],
					[
						112831.85840708,
						7,
						0
					],
					[
						113097.345132743,
						7,
						0
					],
					[
						113362.831858407,
						7,
						0
					],
					[
						113628.318584071,
						6,
						0
					],
					[
						113893.805309734,
						6,
						0
					],
					[
						114159.292035398,
						6,
						0
					],
					[
						112566.371681416,
						6,
						0
					],
					[
						113628.318584071,
						5,
						0
					],
					[
						114026.548672566,
						1,
						0
					]
				],
				"typeOfSection": 0,
				"lengthInSteps": 16,
				"gfSection": false,
				"altAnim": false,
				"mustHitSection": false,
				"changeBPM": false,
				"bpm": 113
			},
			{
				"sectionNotes": [
					[
						114955.752212389,
						1,
						132.743362831858
					],
					[
						114690.265486726,
						3,
						132.743362831858
					],
					[
						115221.238938053,
						3,
						0
					],
					[
						115353.982300885,
						3,
						0
					],
					[
						115486.725663717,
						0,
						0
					],
					[
						115752.212389381,
						1,
						0
					],
					[
						115884.955752212,
						2,
						0
					],
					[
						116150.442477876,
						2,
						0
					],
					[
						116017.699115044,
						0,
						0
					],
					[
						116283.185840708,
						3,
						0
					],
					[
						116349.557522124,
						1,
						0
					],
					[
						116415.92920354,
						0,
						0
					],
					[
						116548.672566372,
						3,
						0
					],
					[
						116482.300884956,
						2,
						0
					],
					[
						116681.415929204,
						2,
						132.743362831858
					],
					[
						115752.212389381,
						3,
						0
					]
				],
				"typeOfSection": 0,
				"lengthInSteps": 16,
				"gfSection": false,
				"altAnim": false,
				"mustHitSection": true,
				"changeBPM": false,
				"bpm": 113
			},
			{
				"sectionNotes": [
					[
						116946.902654867,
						0,
						0
					],
					[
						117079.646017699,
						1,
						0
					],
					[
						117212.389380531,
						3,
						0
					],
					[
						117345.132743363,
						0,
						132.743362831858
					],
					[
						117610.619469027,
						3,
						0
					],
					[
						117743.362831858,
						3,
						0
					],
					[
						118008.849557522,
						3,
						0
					],
					[
						118407.079646018,
						2,
						0
					],
					[
						118672.566371681,
						1,
						0
					],
					[
						118539.82300885,
						3,
						0
					],
					[
						118815.265486726,
						0,
						0
					],
					[
						118141.592920354,
						0,
						0
					],
					[
						118207.96460177,
						1,
						0
					],
					[
						118274.336283186,
						0,
						0
					],
					[
						118340.707964602,
						1,
						0
					],
					[
						117876.10619469,
						2,
						0
					],
					[
						117942.477876106,
						1,
						0
					],
					[
						118274.336283186,
						3,
						0
					]
				],
				"typeOfSection": 0,
				"lengthInSteps": 16,
				"gfSection": false,
				"altAnim": false,
				"mustHitSection": true,
				"changeBPM": false,
				"bpm": 113
			},
			{
				"sectionNotes": [
					[
						119203.539823009,
						0,
						0
					],
					[
						119336.283185841,
						0,
						0
					],
					[
						119469.026548673,
						1,
						0
					],
					[
						119734.513274336,
						0,
						0
					],
					[
						120000,
						2,
						0
					],
					[
						120265.486725664,
						3,
						0
					],
					[
						120530.973451327,
						1,
						0
					],
					[
						120663.716814159,
						1,
						0
					],
					[
						120796.460176991,
						0,
						132.743362831858
					],
					[
						119469.026548673,
						3,
						0
					],
					[
						120000,
						1,
						0
					]
				],
				"typeOfSection": 0,
				"lengthInSteps": 16,
				"gfSection": false,
				"altAnim": false,
				"mustHitSection": false,
				"changeBPM": false,
				"bpm": 113
			},
			{
				"sectionNotes": [
					[
						121194.690265487,
						2,
						0
					],
					[
						121460.17699115,
						2,
						0
					],
					[
						121592.920353982,
						0,
						132.743362831858
					],
					[
						122389.380530973,
						1,
						0
					],
					[
						122522.123893805,
						3,
						0
					],
					[
						122654.867256637,
						0,
						0
					],
					[
						122787.610619469,
						2,
						0
					],
					[
						122920.353982301,
						3,
						0
					],
					[
						123053.097345133,
						0,
						0
					],
					[
						121858.407079646,
						1,
						132.743362831858
					],
					[
						122123.89380531,
						3,
						0
					],
					[
						122123.89380531,
						0,
						0
					],
					[
						122522.123893805,
						2,
						0
					],
					[
						122920.353982301,
						1,
						0
					]
				],
				"typeOfSection": 0,
				"lengthInSteps": 16,
				"gfSection": false,
				"altAnim": false,
				"mustHitSection": false,
				"changeBPM": false,
				"bpm": 113
			},
			{
				"sectionNotes": [
					[
						123517.699115044,
						0,
						0
					],
					[
						124380.530973451,
						1,
						0
					],
					[
						123185.840707965,
						2,
						0
					],
					[
						123318.584070796,
						2,
						0
					],
					[
						123451.327433628,
						3,
						0
					],
					[
						123584.07079646,
						3,
						0
					],
					[
						124778.761061947,
						0,
						0
					],
					[
						124911.504424779,
						0,
						0
					],
					[
						123650.442477876,
						0,
						0
					],
					[
						123849.557522124,
						2,
						0
					],
					[
						123716.814159292,
						2,
						0
					],
					[
						123982.300884956,
						0,
						0
					],
					[
						124115.044247788,
						3,
						0
					],
					[
						124513.274336283,
						2,
						0
					],
					[
						125044.247787611,
						1,
						132.743362831858
					]
				],
				"typeOfSection": 0,
				"lengthInSteps": 16,
				"gfSection": false,
				"altAnim": false,
				"mustHitSection": false,
				"changeBPM": false,
				"bpm": 113
			},
			{
				"sectionNotes": [
					[
						125442.477876106,
						0,
						0
					],
					[
						125309.734513274,
						2,
						0
					],
					[
						125707.96460177,
						2,
						0
					],
					[
						126371.681415929,
						3,
						0
					],
					[
						125840.707964602,
						0,
						0
					],
					[
						125973.451327434,
						0,
						0
					],
					[
						126106.194690265,
						0,
						0
					],
					[
						126238.938053097,
						1,
						0
					],
					[
						126305.309734513,
						1,
						0
					],
					[
						126172.566371681,
						2,
						0
					],
					[
						126769.911504425,
						3,
						0
					],
					[
						126637.168141593,
						1,
						0
					],
					[
						126902.654867257,
						1,
						0
					],
					[
						127035.398230088,
						0,
						0
					],
					[
						127168.14159292,
						3,
						0
					],
					[
						127300.884955752,
						1,
						0
					],
					[
						125309.734513274,
						3,
						0
					],
					[
						125707.96460177,
						3,
						0
					],
					[
						126371.681415929,
						0,
						0
					],
					[
						126769.911504425,
						0,
						0
					]
				],
				"typeOfSection": 0,
				"lengthInSteps": 16,
				"gfSection": false,
				"altAnim": false,
				"mustHitSection": false,
				"changeBPM": false,
				"bpm": 113
			},
			{
				"sectionNotes": [
					[
						127699.115044248,
						1,
						0
					],
					[
						127831.85840708,
						1,
						0
					],
					[
						128495.575221239,
						3,
						132.743362831858
					],
					[
						128761.061946903,
						0,
						132.743362831858
					],
					[
						129026.548672566,
						2,
						0
					],
					[
						129159.292035398,
						2,
						0
					],
					[
						129292.03539823,
						1,
						132.743362831858
					],
					[
						128230.088495575,
						1,
						132.743362831858
					],
					[
						127964.601769912,
						0,
						132.743362831858
					],
					[
						128495.575221239,
						0,
						0
					],
					[
						127964.601769912,
						2,
						0
					]
				],
				"typeOfSection": 0,
				"lengthInSteps": 16,
				"gfSection": false,
				"altAnim": false,
				"mustHitSection": true,
				"changeBPM": false,
				"bpm": 113
			},
			{
				"sectionNotes": [
					[
						129690.265486726,
						2,
						0
					],
					[
						129955.752212389,
						2,
						0
					],
					[
						130088.495575221,
						0,
						132.743362831858
					],
					[
						130353.982300885,
						3,
						132.743362831858
					],
					[
						130619.469026549,
						0,
						132.743362831858
					],
					[
						130884.955752212,
						1,
						0
					],
					[
						131017.699115044,
						3,
						0
					],
					[
						131150.442477876,
						0,
						0
					],
					[
						131283.185840708,
						2,
						0
					],
					[
						131415.92920354,
						3,
						0
					],
					[
						131548.672566372,
						0,
						0
					],
					[
						130619.469026549,
						2,
						0
					],
					[
						131017.699115044,
						2,
						0
					],
					[
						131415.92920354,
						1,
						0
					]
				],
				"typeOfSection": 0,
				"lengthInSteps": 16,
				"gfSection": false,
				"altAnim": false,
				"mustHitSection": true,
				"changeBPM": false,
				"bpm": 113
			},
			{
				"sectionNotes": [
					[
						132013.274336283,
						0,
						0
					],
					[
						132477.876106195,
						0,
						0
					],
					[
						132610.619469027,
						3,
						132.743362831858
					],
					[
						132876.10619469,
						1,
						0
					],
					[
						133008.849557522,
						2,
						132.743362831858
					],
					[
						131681.415929204,
						2,
						0
					],
					[
						131814.159292035,
						2,
						0
					],
					[
						131946.902654867,
						3,
						0
					],
					[
						132079.646017699,
						3,
						0
					],
					[
						133274.336283186,
						0,
						0
					],
					[
						133407.079646018,
						0,
						0
					],
					[
						133539.82300885,
						1,
						132.743362831858
					],
					[
						132146.017699115,
						0,
						0
					],
					[
						132212.389380531,
						2,
						0
					],
					[
						132345.132743363,
						2,
						0
					]
				],
				"typeOfSection": 0,
				"lengthInSteps": 16,
				"gfSection": false,
				"altAnim": false,
				"mustHitSection": true,
				"changeBPM": false,
				"bpm": 113
			},
			{
				"sectionNotes": [
					[
						133805.309734513,
						3,
						0
					],
					[
						133938.053097345,
						0,
						0
					],
					[
						134203.539823009,
						3,
						0
					],
					[
						134668.14159292,
						3,
						0
					],
					[
						134867.256637168,
						2,
						132.743362831858
					],
					[
						135663.716814159,
						3,
						0
					],
					[
						135796.460176991,
						1,
						0
					],
					[
						134734.513274336,
						0,
						0
					],
					[
						134734.513274336,
						0,
						0
					],
					[
						134800.884955752,
						1,
						0
					],
					[
						134469.026548673,
						1,
						0
					],
					[
						134601.769911504,
						1,
						0
					],
					[
						134336.283185841,
						1,
						0
					],
					[
						135132.743362832,
						0,
						0
					],
					[
						135265.486725664,
						2,
						0
					],
					[
						135398.230088496,
						0,
						0
					],
					[
						135530.973451327,
						1,
						0
					],
					[
						133805.309734513,
						2,
						0
					],
					[
						134203.539823009,
						2,
						0
					],
					[
						134867.256637168,
						0,
						0
					],
					[
						135265.486725664,
						1,
						0
					]
				],
				"typeOfSection": 0,
				"lengthInSteps": 16,
				"gfSection": false,
				"altAnim": false,
				"mustHitSection": true,
				"changeBPM": false,
				"bpm": 113
			},
			{
				"sectionNotes": [
					[
						135929.203539823,
						1,
						132.743362831858
					],
					[
						136194.690265487,
						3,
						0
					],
					[
						136327.433628319,
						1,
						0
					],
					[
						136592.920353982,
						0,
						0
					],
					[
						136858.407079646,
						0,
						0
					],
					[
						136991.150442478,
						3,
						132.743362831858
					],
					[
						136725.663716814,
						2,
						0
					],
					[
						137522.123893805,
						3,
						132.743362831858
					],
					[
						137256.637168142,
						2,
						0
					],
					[
						137787.610619469,
						2,
						0
					],
					[
						137920.353982301,
						1,
						0
					],
					[
						135929.203539823,
						7,
						1991.15044247788
					]
				],
				"typeOfSection": 0,
				"lengthInSteps": 16,
				"gfSection": false,
				"altAnim": false,
				"mustHitSection": false,
				"changeBPM": false,
				"bpm": 113
			},
			{
				"sectionNotes": [
					[
						138053.097345133,
						0,
						0
					],
					[
						138318.584070796,
						0,
						0
					],
					[
						138451.327433628,
						0,
						0
					],
					[
						138982.300884956,
						3,
						0
					],
					[
						138849.557522124,
						1,
						0
					],
					[
						139115.044247788,
						2,
						132.743362831858
					],
					[
						139380.530973451,
						0,
						0
					],
					[
						139513.274336283,
						1,
						0
					],
					[
						139646.017699115,
						2,
						0
					],
					[
						139911.504424779,
						2,
						0
					],
					[
						140044.247787611,
						0,
						0
					],
					[
						138716.814159292,
						0,
						0
					],
					[
						138053.097345133,
						4,
						663.716814159292
					],
					[
						138849.557522124,
						5,
						663.716814159292
					],
					[
						139646.017699115,
						6,
						663.716814159292
					],
					[
						140044.247787611,
						4,
						265.486725663717
					]
				],
				"typeOfSection": 0,
				"lengthInSteps": 16,
				"gfSection": false,
				"altAnim": false,
				"mustHitSection": false,
				"changeBPM": false,
				"bpm": 113
			},
			{
				"sectionNotes": [
					[
						140176.991150443,
						1,
						132.743362831858
					],
					[
						140442.477876106,
						3,
						0
					],
					[
						140575.221238938,
						1,
						0
					],
					[
						141106.194690266,
						0,
						0
					],
					[
						140707.96460177,
						2,
						0
					],
					[
						140840.707964602,
						3,
						0
					],
					[
						140973.451327434,
						2,
						0
					],
					[
						141371.681415929,
						0,
						0
					],
					[
						141438.053097345,
						3,
						0
					],
					[
						141305.309734513,
						2,
						0
					],
					[
						141238.938053097,
						1,
						0
					],
					[
						141504.424778761,
						2,
						0
					],
					[
						141769.911504425,
						0,
						132.743362831858
					],
					[
						142035.398230089,
						3,
						0
					],
					[
						142168.14159292,
						2,
						0
					],
					[
						140442.477876106,
						7,
						1725.66371681416
					]
				],
				"typeOfSection": 0,
				"lengthInSteps": 16,
				"gfSection": false,
				"altAnim": false,
				"mustHitSection": false,
				"changeBPM": false,
				"bpm": 113
			},
			{
				"sectionNotes": [
					[
						142300.884955752,
						1,
						0
					],
					[
						142433.628318584,
						3,
						0
					],
					[
						142566.371681416,
						3,
						0
					],
					[
						142699.115044248,
						1,
						0
					],
					[
						142831.85840708,
						3,
						0
					],
					[
						142964.601769912,
						1,
						0
					],
					[
						143097.345132743,
						0,
						0
					],
					[
						143230.088495575,
						3,
						0
					],
					[
						143362.831858407,
						2,
						132.743362831858
					],
					[
						143628.318584071,
						0,
						0
					],
					[
						143893.805309735,
						3,
						0
					],
					[
						143926.991150443,
						2,
						132.743362831858
					],
					[
						143761.061946903,
						1,
						0
					],
					[
						144159.292035398,
						0,
						132.743362831858
					],
					[
						142300.884955752,
						4,
						0
					],
					[
						142433.628318584,
						6,
						0
					],
					[
						142566.371681416,
						7,
						0
					],
					[
						142699.115044248,
						5,
						0
					],
					[
						142831.85840708,
						6,
						0
					],
					[
						142964.601769912,
						7,
						0
					],
					[
						143097.345132743,
						4,
						0
					],
					[
						143230.088495575,
						7,
						0
					],
					[
						143362.831858407,
						5,
						132.743362831858
					],
					[
						143628.318584071,
						7,
						132.743362831858
					],
					[
						143893.805309735,
						4,
						265.486725663717
					]
				],
				"typeOfSection": 0,
				"lengthInSteps": 16,
				"gfSection": false,
				"altAnim": false,
				"mustHitSection": false,
				"changeBPM": false,
				"bpm": 113
			},
			{
				"sectionNotes": [
					[
						144424.778761062,
						1,
						132.743362831858
					],
					[
						144690.265486726,
						3,
						0
					],
					[
						144823.008849558,
						1,
						0
					],
					[
						145088.495575221,
						0,
						0
					],
					[
						145353.982300885,
						0,
						0
					],
					[
						145486.725663717,
						3,
						132.743362831858
					],
					[
						145221.238938053,
						2,
						0
					],
					[
						146017.699115044,
						3,
						132.743362831858
					],
					[
						145752.212389381,
						2,
						0
					],
					[
						146283.185840708,
						2,
						0
					],
					[
						146415.92920354,
						1,
						0
					],
					[
						144424.778761062,
						6,
						265.486725663717
					]
				],
				"typeOfSection": 0,
				"lengthInSteps": 16,
				"gfSection": false,
				"altAnim": false,
				"mustHitSection": true,
				"changeBPM": false,
				"bpm": 113
			},
			{
				"sectionNotes": [
					[
						146548.672566372,
						0,
						0
					],
					[
						146814.159292035,
						0,
						0
					],
					[
						146946.902654867,
						0,
						0
					],
					[
						147477.876106195,
						3,
						0
					],
					[
						147345.132743363,
						1,
						0
					],
					[
						147610.619469027,
						2,
						132.743362831858
					],
					[
						147876.10619469,
						0,
						0
					],
					[
						148008.849557522,
						1,
						0
					],
					[
						148141.592920354,
						2,
						0
					],
					[
						148407.079646018,
						2,
						0
					],
					[
						148539.82300885,
						0,
						0
					],
					[
						147212.389380531,
						0,
						0
					],
					[
						146548.672566372,
						4,
						265.486725663717
					],
					[
						147345.132743363,
						5,
						265.486725663717
					],
					[
						148141.592920354,
						4,
						265.486725663717
					],
					[
						148274.336283186,
						5,
						132.743362831858
					]
				],
				"typeOfSection": 0,
				"lengthInSteps": 16,
				"gfSection": false,
				"altAnim": false,
				"mustHitSection": true,
				"changeBPM": false,
				"bpm": 113
			},
			{
				"sectionNotes": [
					[
						148672.566371681,
						1,
						132.743362831858
					],
					[
						148938.053097345,
						3,
						0
					],
					[
						149070.796460177,
						1,
						0
					],
					[
						149601.769911504,
						0,
						0
					],
					[
						149203.539823009,
						2,
						0
					],
					[
						149336.283185841,
						3,
						0
					],
					[
						149469.026548673,
						2,
						0
					],
					[
						149867.256637168,
						0,
						0
					],
					[
						149933.628318584,
						3,
						0
					],
					[
						149800.884955752,
						2,
						0
					],
					[
						149734.513274336,
						1,
						0
					],
					[
						150000,
						2,
						0
					],
					[
						150265.486725664,
						0,
						132.743362831858
					],
					[
						150530.973451327,
						3,
						0
					],
					[
						150663.716814159,
						2,
						0
					],
					[
						148938.053097345,
						7,
						265.486725663717
					]
				],
				"typeOfSection": 0,
				"lengthInSteps": 16,
				"gfSection": false,
				"altAnim": false,
				"mustHitSection": true,
				"changeBPM": false,
				"bpm": 113
			},
			{
				"sectionNotes": [
					[
						150796.460176991,
						1,
						0
					],
					[
						150929.203539823,
						3,
						0
					],
					[
						151061.946902655,
						3,
						0
					],
					[
						151194.690265487,
						1,
						0
					],
					[
						151327.433628319,
						3,
						0
					],
					[
						151460.17699115,
						1,
						0
					],
					[
						151592.920353982,
						0,
						0
					],
					[
						151725.663716814,
						3,
						0
					],
					[
						151858.407079646,
						2,
						132.743362831858
					],
					[
						152123.89380531,
						0,
						0
					],
					[
						152389.380530973,
						3,
						0
					],
					[
						152422.566371681,
						2,
						132.743362831858
					],
					[
						152256.637168142,
						1,
						0
					],
					[
						152654.867256637,
						0,
						132.743362831858
					],
					[
						150796.460176991,
						4,
						0
					],
					[
						151061.946902655,
						7,
						0
					],
					[
						151725.663716814,
						7,
						0
					],
					[
						151858.407079646,
						5,
						0
					],
					[
						151194.690265487,
						6,
						0
					],
					[
						150929.203539823,
						5,
						0
					],
					[
						151327.433628319,
						7,
						0
					],
					[
						151460.17699115,
						4,
						0
					],
					[
						151592.920353982,
						6,
						0
					],
					[
						152123.89380531,
						4,
						0
					],
					[
						152389.380530973,
						6,
						265.486725663717
					]
				],
				"typeOfSection": 0,
				"lengthInSteps": 16,
				"gfSection": false,
				"altAnim": false,
				"mustHitSection": true,
				"changeBPM": false,
				"bpm": 113
			},
			{
				"sectionNotes": [
					[
						152920.353982301,
						3,
						929.203539823009
					],
					[
						152920.353982301,
						4,
						265.486725663717
					]
				],
				"typeOfSection": 0,
				"lengthInSteps": 16,
				"gfSection": false,
				"altAnim": false,
				"mustHitSection": true,
				"changeBPM": false,
				"bpm": 113
			},
			{
				"sectionNotes": [],
				"typeOfSection": 0,
				"lengthInSteps": 16,
				"gfSection": false,
				"altAnim": false,
				"mustHitSection": true,
				"changeBPM": false,
				"bpm": 113
			},
			{
				"sectionNotes": [],
				"typeOfSection": 0,
				"lengthInSteps": 16,
				"gfSection": false,
				"altAnim": false,
				"mustHitSection": false,
				"changeBPM": false,
				"bpm": 113
			},
			{
				"sectionNotes": [],
				"typeOfSection": 0,
				"lengthInSteps": 16,
				"gfSection": false,
				"altAnim": false,
				"mustHitSection": false,
				"changeBPM": false,
				"bpm": 113
			},
			{
				"sectionNotes": [],
				"typeOfSection": 0,
				"lengthInSteps": 16,
				"gfSection": false,
				"altAnim": false,
				"mustHitSection": true,
				"changeBPM": false,
				"bpm": 113
			},
			{
				"sectionNotes": [],
				"typeOfSection": 0,
				"lengthInSteps": 16,
				"gfSection": false,
				"altAnim": false,
				"mustHitSection": true,
				"changeBPM": false,
				"bpm": 113
			},
			{
				"sectionNotes": [],
				"typeOfSection": 0,
				"lengthInSteps": 16,
				"gfSection": false,
				"altAnim": false,
				"mustHitSection": false,
				"changeBPM": false,
				"bpm": 113
			},
			{
				"sectionNotes": [],
				"typeOfSection": 0,
				"lengthInSteps": 16,
				"gfSection": false,
				"altAnim": false,
				"mustHitSection": false,
				"changeBPM": false,
				"bpm": 113
			},
			{
				"sectionNotes": [],
				"typeOfSection": 0,
				"lengthInSteps": 16,
				"gfSection": false,
				"altAnim": false,
				"mustHitSection": false,
				"changeBPM": false,
				"bpm": 113
			},
			{
				"sectionNotes": [],
				"typeOfSection": 0,
				"lengthInSteps": 16,
				"gfSection": false,
				"altAnim": false,
				"mustHitSection": false,
				"changeBPM": false,
				"bpm": 113
			},
			{
				"sectionNotes": [],
				"typeOfSection": 0,
				"lengthInSteps": 16,
				"gfSection": false,
				"altAnim": false,
				"mustHitSection": true,
				"changeBPM": false,
				"bpm": 113
			},
			{
				"gfSection": false,
				"lengthInSteps": 16,
				"altAnim": false,
				"typeOfSection": 0,
				"sectionNotes": [],
				"bpm": 113,
				"changeBPM": false,
				"mustHitSection": true
			}
		],
		"player2": "ticking",
		"player3": null,
		"song": "Ticking",
		"arrowSkin": "NOTE_assets_3D",
		"needsVoices": true,
		"stage": "ticky",
		"validScore": true,
		"sections": 1,
		"speed": 3.1,
		"bpm": 113
	}
}